keks/__init__.py
keks/__main__.py
keks-0.0.0.post3.dist-info/entry_points.txt
keks-0.0.0.post3.dist-info/LICENSE
keks-0.0.0.post3.dist-info/WHEEL
keks-0.0.0.post3.dist-info/METADATA
keks-0.0.0.post3.dist-info/RECORD
