Metadata-Version: 2.1
Name: keks
Version: 0.0.0.post3
Summary: for a school project
Keywords: 
Requires-Python: ~=3.11
Classifier: Topic :: Education
Classifier: Natural Language :: German
Classifier: Operating System :: OS Independent
Classifier: Programming Language :: Python :: 3
Classifier: License :: OSI Approved :: MIT License
Requires-Dist: typer[all]
Project-URL: Author, https://github.com/katzensindniedlich
Project-URL: Source, https://github.com/katzensindniedlich/keks
Project-URL: Webpage, https://schokokeks.pages.dev
